hipchat/__init__.py
python_hipchat_v1-0.3.5.dist-info/DESCRIPTION.rst
python_hipchat_v1-0.3.5.dist-info/METADATA
python_hipchat_v1-0.3.5.dist-info/metadata.json
python_hipchat_v1-0.3.5.dist-info/RECORD
python_hipchat_v1-0.3.5.dist-info/top_level.txt
python_hipchat_v1-0.3.5.dist-info/WHEEL
