Metadata-Version: 2.0
Name: python-hipchat-v1
Version: 0.3.5
Summary: Easy peasy wrapper for HipChat's v1 API (modified version and credits to kurttheviking)
Home-page: https://github.com/greenietea/python-hipchat-v1
Author: Greenie
Author-email: hello@greenie.ninja
License: MIT
Platform: UNKNOWN
Classifier: Development Status :: 5 - Production/Stable
Classifier: Intended Audience :: Developers
Classifier: License :: OSI Approved :: MIT License
Classifier: Programming Language :: Python :: 2
Classifier: Programming Language :: Python :: 2.7
Classifier: Programming Language :: Python :: 3
Classifier: Programming Language :: Python :: 3.3
Classifier: Programming Language :: Python :: Implementation :: CPython
